TFGENZOO/__init__.py
TFGENZOO/__version__.py
TFGENZOO/flows/__init__.py
TFGENZOO/flows/actnorm.py
TFGENZOO/flows/actnorm_test.py
TFGENZOO/flows/affine_coupling.py
TFGENZOO/flows/affine_coupling_test.py
TFGENZOO/flows/cond_affine_coupling.py
TFGENZOO/flows/cond_affine_coupling_test.py
TFGENZOO/flows/factor_out.py
TFGENZOO/flows/flatten.py
TFGENZOO/flows/flowbase.py
TFGENZOO/flows/flowmodel.py
TFGENZOO/flows/inv1x1conv.py
TFGENZOO/flows/inv1x1conv_test.py
TFGENZOO/flows/quantize.py
TFGENZOO/flows/quantize_test.py
TFGENZOO/flows/squeeze.py
TFGENZOO/flows/squeeze_test.py
TFGENZOO/flows/unsafe/__init__.py
TFGENZOO/flows/unsafe/actnorm.py
TFGENZOO/flows/unsafe/actnorm_test.py
TFGENZOO/flows/utils/__init__.py
TFGENZOO/flows/utils/actnorm_activation.py
TFGENZOO/flows/utils/conv.py
TFGENZOO/flows/utils/conv_test.py
TFGENZOO/flows/utils/conv_zeros.py
TFGENZOO/flows/utils/conv_zeros_test.py
TFGENZOO/flows/utils/gaussianize.py
TFGENZOO/flows/utils/util.py
TFGENZOO/flows/utils/unsafe/__init__.py
TFGENZOO/flows/utils/unsafe/actnorm_activation.py
TFGENZOO/gans/__init__.py
TFGENZOO/layers/__init__.py
TFGENZOO/layers/flowtts_coupling.py
TFGENZOO/layers/flowtts_coupling_test.py
TFGENZOO/layers/resnet.py
TFGENZOO/layers/spadebn.py
TFGENZOO/layers/spectral_normalization.py
TFGENZOO/layers/weight_norm.py
TFGENZOO/optimizers/__init__.py
TFGENZOO/optimizers/transformer_schedule.py
TFGENZOO-1.2.5.dist-info/METADATA
TFGENZOO-1.2.5.dist-info/WHEEL
TFGENZOO-1.2.5.dist-info/top_level.txt
TFGENZOO-1.2.5.dist-info/RECORD
