Metadata-Version: 2.1
Name: TFGENZOO
Version: 1.2.5
Summary: helper of building generative model with Tensorflow 2.x
Home-page: https://github.com/MokkeMeguru/TFGENZOO
Author: MokkeMeguru
Author-email: meguru.mokke@gmail.com
License: MIT
Platform: UNKNOWN
Classifier: Programming Language :: Python :: 3.7
Classifier: Programming Language :: Python :: 3.6
Classifier: License :: OSI Approved :: MIT License
Classifier: Operating System :: POSIX :: Linux
Classifier: Operating System :: Microsoft :: Windows
Classifier: Environment :: GPU :: NVIDIA CUDA :: 10.0
Classifier: Environment :: GPU :: NVIDIA CUDA :: 10.1
Requires-Dist: tensorflow (>=2.4.0)
Requires-Dist: tensorflow-probability (>=0.10.1)
Requires-Dist: pandas
